MANIFEST.in
setup.py
scripts/snakepit
snakepit/__init__.py
snakepit/main.py
snakepit.egg-info/PKG-INFO
snakepit.egg-info/SOURCES.txt
snakepit.egg-info/dependency_links.txt
snakepit.egg-info/requires.txt
snakepit.egg-info/top_level.txt
snakepit.egg-info/zip-safe
snakepit/templates/TEMPLATE-PyRun.spec
snakepit/templates/TEMPLATE-miniconda.spec