Metadata-Version: 1.1
Name: snakepit
Version: 178
Summary: Package Python software as an RPM including all dependencies (even the interpreter).
Home-page: https://github.com/ImmobilienScout24/snakepit
Author: Valentin Haenel
Author-email: valentin@haenel.co
License: Apache
Platform: UNKNOWN
Classifier: Development Status :: 2 - Pre-Alpha
Classifier: Environment :: Console
Classifier: Intended Audience :: Developers
Classifier: Intended Audience :: System Administrators
Classifier: License :: OSI Approved :: Apache Software License
Classifier: Programming Language :: Python
Classifier: Operating System :: POSIX :: Linux
Classifier: Topic :: System :: Software Distribution
Classifier: Topic :: System :: Systems Administration
Classifier: Topic :: System :: Archiving :: Packaging
Classifier: Topic :: Utilities
